kson/__init__.py
kson/core.py
kson_lib-1.0.0.dist-info/METADATA
kson_lib-1.0.0.dist-info/WHEEL
kson_lib-1.0.0.dist-info/top_level.txt
kson_lib-1.0.0.dist-info/RECORD
