Metadata-Version: 2.1
Name: kson-lib
Version: 1.0.0
Summary: KSON (Kompact Structured Object Notation) - JSON with comments support
Home-page: UNKNOWN
Author: dnoxie
License: UNKNOWN
Platform: UNKNOWN
Classifier: Programming Language :: Python :: 3
Classifier: License :: OSI Approved :: MIT License
Classifier: Operating System :: OS Independent
Requires-Python: >=3.6
